<?xml version="1.0" encoding="UTF-8"?>
 
<databaseChangeLog xmlns="http://www.liquibase.org/xml/ns/dbchangelog/1.9"
                   xmlns:xsi="http://www.w3.org/2001/XMLSchema-instance"
                   xsi:schemaLocation="http://www.liquibase.org/xml/ns/dbchangelog/1.9
                  http://www.liquibase.org/xml/ns/dbchangelog/dbchangelog-1.9.xsd">
 
    <!--
    	See http://wiki.openmrs.org/display/docs/Module+liquibase+File for 
    	documentation on this file.
    
        See http://www.liquibase.org/manual/home#available_database_refactorings
        for a list of supported elements and attributes
    -->
 
 	<!-- Uncomment the changeset below if you want to make the Item class persistable, see also Item and BahminischedulingDaoTest -->
 	<!--
	<changeSet id="bahminischeduling-2016-08-02-12-21" author="raff">
		<preConditions onFail="MARK_RAN">
			<not><tableExists tableName="bahminischeduling_item"/></not>
		</preConditions>
		<comment>
			Creating the bahminischeduling_item table
		</comment>
		<createTable tableName="bahminischeduling_item">
			<column name="bahminischeduling_item_id" type="int" autoIncrement="true">
				<constraints primaryKey="true" nullable="false"/>
			</column>
			<column name="uuid" type="char(38)">
				<constraints nullable="false" unique="true"></constraints>
			</column>
			<column name="owner" type="int" />
			<column name="description" type="varchar(255)" />
		</createTable>
        <addForeignKeyConstraint constraintName="bahminischeduling_item_owner_fk" baseTableName="bahminischeduling_item" baseColumnNames="owner"  referencedTableName="users"
                                 referencedColumnNames="user_id" />
    </changeSet> -->
 
 	<changeSet author="liquibase-docs" id="pat-appt-reminder">
 	<preConditions onFail="MARK_RAN">
			<not><tableExists tableName="patient_appointment_reminder"/></not>
		</preConditions>
		<comment>
			Creating the patient_appointment_reminder table
		</comment>
		<createTable tableName="patient_appointment_reminder">
			<column name="id" type="int(11)" autoIncrement="true">
				<constraints primaryKey="true" nullable="false"/>
			</column>
			<column name="patient_appointment_id" type="int(11)">
				<constraints nullable="true"></constraints>
			</column>
			<column name="patient_id" type="int(11)">
				<constraints nullable="true"></constraints>
			</column>
			<column name="start_date_time" type="datetime">
				<constraints nullable="true"></constraints>
			</column>
			<column name="end_date_time" type="datetime">
				<constraints nullable="true"></constraints>
			</column>
			<column name="appointment_service_id" type="int(11)">
				<constraints nullable="true"></constraints>
			</column>
			<column name="appointment_service_type_id" type="int(11)">
				<constraints nullable="true"></constraints>
			</column>
			<column name="status" type="varchar(45)">
				<constraints nullable="true"></constraints>
			</column>
			<column name="consent" type="varchar(45)">
				<constraints nullable="true"></constraints>
			</column>			
			<column name="sms_status_one_day" type="varchar(45)">
				<constraints nullable="true"></constraints>
			</column>			
			<column name="sms_status_seven_day" type="varchar(45)">
				<constraints nullable="true"></constraints>
			</column>			
			
		</createTable>
	</changeSet>
	
	<changeSet author="liquibase-docs" id="data-load">
	 	<preConditions onFail="MARK_RAN">
			<not><tableExists tableName="data_load"/></not>
		</preConditions>
		<comment>
			Creating the data_load table
		</comment>
		<createTable tableName="data_load">
			<column name="id" type="int(11)" autoIncrement="true">
				<constraints primaryKey="true" nullable="false"/>
			</column>
			<column name="data_loaded_check" type="varchar(10)">
				<constraints nullable="true"></constraints>
			</column>
		</createTable>
	</changeSet>
	
	<changeSet author="liquibase-docs" id="appt-reminder-log">
 	<preConditions onFail="MARK_RAN">
			<not><tableExists tableName="appointment_reminder_log"/></not>
		</preConditions>
		<comment>
			Creating the patient_appointment_reminder table
		</comment>
		<createTable tableName="appointment_reminder_log">
			<column name="id" type="int(11)" autoIncrement="true">
				<constraints primaryKey="true" nullable="false"/>
			</column>
			<column name="message" type="varchar(12000)">
				<constraints nullable="true"></constraints>
			</column>
			<column name="patient_appointment_ids_one_day" type="varchar(45)">
				<constraints nullable="true"></constraints>
			</column>
			<column name="patient_id" type="int(11)">
				<constraints nullable="true"></constraints>
			</column>
			<column name="sent_on" type="datetime">
				<constraints nullable="true"></constraints>
			</column>
			<column name="contactNumber" type="varchar(45)">
				<constraints nullable="true"></constraints>
			</column>
			<column name="messagesid" type="varchar(300)">
				<constraints nullable="true"></constraints>
			</column>
			<column name="messagingServiceSid" type="varchar(300)">
				<constraints nullable="true"></constraints>
			</column>
			<column name="error_code" type="int(11)">
				<constraints nullable="true"></constraints>
			</column>			
			<column name="errorMessage" type="varchar(300)">
				<constraints nullable="true"></constraints>
			</column>			
			<column name="patient_appointment_ids_one_week" type="varchar(45)">
				<constraints nullable="true"></constraints>
			</column>			
		</createTable>
	</changeSet>
	
	<changeSet author="liquibase-docs" id="dropTable-ABC">
	    <preConditions onFail="MARK_RAN"><tableExists tableName="sms_language"/></preConditions>
	    <dropTable cascadeConstraints="true"
	            tableName="sms_language"/>
	</changeSet>

	<changeSet author="liquibase-docs" id="language">
	 	<preConditions onFail="MARK_RAN">
			<not><tableExists tableName="sms_language"/></not>
		</preConditions>
		<comment>
			Creating the sms_language table
		</comment>
		<createTable tableName="sms_language">
			<column name="id" type="int(11)" autoIncrement="true">
				<constraints primaryKey="true" nullable="false"/>
			</column>
			<column name="text_message" type="varchar(200)">
				<constraints nullable="false"></constraints>
			</column>
			<column name="locale" type="varchar(50)">
				<constraints nullable="false"></constraints>
			</column>
			<column name="day" type="int">
				<constraints nullable="false"></constraints>
			</column>
		</createTable>
	</changeSet>
	
	<changeSet author="ABC" id="insert-to-scheduler-table">
    	<insert tableName="scheduler_task_config">
	        <column name="name" value="Bahmini SMS Scheduler"/>
	        <column name="description" value="Bahmini SMS Scheduler"/>
	        <column name="schedulable_class" value="org.openmrs.module.bahminischeduling.BahminiSmsScheduler"/>
	        <column name="start_time" value="2018-09-06 09:30:00"/>
	        <column name="start_time_pattern"/>
	        <column name="repeat_interval" value="10000"/>
	        <column name="start_on_startup" value="1"/>
	        <column name="started" value="1"/>
	        <column name="created_by" value="1"/>
	        <column name="date_created" value="2018-09-06 09:30:00"/>
	        <column name="changed_by" defaultValue="null"/>
	        <column name="date_changed" defaultValue="null"/>
	        <column name="last_execution_time" defaultValue="null"/>
	        <column name="uuid" value="uuid()"/>
    	</insert>
	</changeSet>
	
	<changeSet author="ABC" id="insert-to-sms-table">
	    <insert tableName="sms_language">
	        <!-- <column name="text_message" value=" پر مقرر ہے (DATE) APPOINTMENT_SERVICE کے لئے تقرری "/> -->
	        <column name="text_message" value="ٹائٹل - آپ کی 'سروس' کے لئے ملاقات 'تاریخ' پر طے شدہ ہے"/>
	        <column name="locale" value="Urdu"/>
	        <column name="day" valueNumeric="1"/>
	    </insert>
	    <insert tableName="sms_language">
	        <column name="text_message" value="ٹائٹل - آپ کی 'سروس' کے لئے ملاقات 'تاریخ' پر طے شدہ ہے"/>
	        <column name="locale" value="Pashtu"/>
	        <column name="day" valueNumeric="1"/>
	    </insert>
	    <insert tableName="sms_language">
	        <column name="text_message" value="ٹائٹل - آپ کی 'سروس' کے لئے ملاقات 'تاریخ' پر طے شدہ ہے"/>
	        <column name="locale" value="Bengali"/>
	        <column name="day" valueNumeric="1"/>
	    </insert>
	    <insert tableName="sms_language">
	        <column name="text_message" value="ٹائٹل - آپ کی 'سروس' کے لئے ملاقات 'تاریخ' پر طے شدہ ہے"/>
	        <column name="locale" value="Sindhi"/>
	        <column name="day" valueNumeric="1"/>
	    </insert>
	
	    <insert tableName="sms_language">
	        <!-- <column name="text_message" value=" پر مقرر ہے (DATE) APPOINTMENT_SERVICE کے لئے تقرری "/> -->
         	<!-- <column name="text_message" value="آپ کی 'APPOINTMENT_SERVICE' کے لئے ملاقات مندرجہ ذیل تاریخ پر طے شدہ ہے"/> -->
         	<column name="text_message" value="ٹائٹل - آپ کی 'سروس' کے لئے ملاقات 'تاریخ' پر طے شدہ ہے"/>
	        <column name="locale" value="Urdu"/>
	        <column name="day" valueNumeric="7"/>
	    </insert>
	    <insert tableName="sms_language">
	        <column name="text_message" value="ٹائٹل - آپ کی 'سروس' کے لئے ملاقات 'تاریخ' پر طے شدہ ہے"/>
	        <column name="locale" value="Pashtu"/>
	        <column name="day" valueNumeric="7"/>
	    </insert>
	    <insert tableName="sms_language">
	        <column name="text_message" value="ٹائٹل - آپ کی 'سروس' کے لئے ملاقات 'تاریخ' پر طے شدہ ہے"/>
	        <column name="locale" value="Bengali"/>
	        <column name="day" valueNumeric="7"/>
	    </insert>
	    <insert tableName="sms_language">
	        <column name="text_message" value="ٹائٹل - آپ کی 'سروس' کے لئے ملاقات 'تاریخ' پر طے شدہ ہے"/>
	        <column name="locale" value="Sindhi"/>
	        <column name="day" valueNumeric="7"/>
	    </insert>
	    
	     <insert tableName="sms_language">
	        <!-- <column name="text_message" value=" پر مقرر ہے (DATE) APPOINTMENT_SERVICE کے لئے تقرری "/> -->
         	<!-- <column name="text_message" value="آپ کی 'APPOINTMENT_SERVICE' کے لئے ملاقات مندرجہ ذیل تاریخ پر طے شدہ ہے"/> -->
         	<column name="text_message" value="ٹائٹل - آپ کی 'سروس' کے لئے ملاقات 'گزشتہ تاریخ' بجے تھی۔ نئ تاریخ کے لئے برائے مہربانی ہمارے نمائیندے سے 03018115153 پر رابطہ کریں"/>
	        <column name="locale" value="Urdu"/>
	        <column name="day" valueNumeric="-1"/>
	    </insert>
	    <insert tableName="sms_language">
	        <column name="text_message" value="ٹائٹل - آپ کی 'سروس' کے لئے ملاقات 'گزشتہ تاریخ' بجے تھی۔ نئ تاریخ کے لئے برائے مہربانی ہمارے نمائیندے سے 03018115153 پر رابطہ کریں"/>
	        <column name="locale" value="Pashtu"/>
	        <column name="day" valueNumeric="-1"/>
	    </insert>
	    <insert tableName="sms_language">
	        <column name="text_message" value="ٹائٹل - آپ کی 'سروس' کے لئے ملاقات 'گزشتہ تاریخ' بجے تھی۔ نئ تاریخ کے لئے برائے مہربانی ہمارے نمائیندے سے 03018115153 پر رابطہ کریں"/>
	        <column name="locale" value="Bengali"/>
	        <column name="day" valueNumeric="-1"/>
	    </insert>
	    <insert tableName="sms_language">
	        <column name="text_message" value="ٹائٹل - آپ کی 'سروس' کے لئے ملاقات 'گزشتہ تاریخ' بجے تھی۔ نئ تاریخ کے لئے برائے مہربانی ہمارے نمائیندے سے 03018115153 پر رابطہ کریں"/>
	        <column name="locale" value="Sindhi"/>
	        <column name="day" valueNumeric="-1"/>
	    </insert>
	</changeSet>
	
	<changeSet author="liquibase-docs" id="dropTable-diagnosisConceptView">
	    <preConditions onFail="MARK_RAN"><tableExists tableName="diagnosis_concept_view"/></preConditions>
	    <dropTable cascadeConstraints="true"
	            tableName="diagnosis_concept_view"/>
	</changeSet>
	
	<changeSet author="liquibase-docs" id="dropView-diagnosisConceptView">
	    <preConditions onFail="MARK_RAN"><viewExists viewName="diagnosis_concept_view"/></preConditions>
	    <dropView viewName="diagnosis_concept_view"/>
	</changeSet>
	
	<changeSet author="liquibase-docs" id="createView-diagnosisConceptView">
    	<createView
            viewName="diagnosis_concept_view">SELECT 
				 1 AS concept_id,
				 1 AS concept_full_name,
				 1 AS concept_short_name,
				 1 AS concept_class_name,
				 1 AS concept_datatype_name,
				 1 AS retired,
				 1 AS description,
				 1 AS date_created,
				 1 AS icd10_code
		</createView>
	</changeSet>
	
	
	<changeSet author="liquibase-docs" id="dropTable-conceptRefTermMap">
	    <preConditions onFail="MARK_RAN"><tableExists tableName="concept_reference_term_map_view"/></preConditions>
	    <dropTable cascadeConstraints="true"
	            tableName="concept_reference_term_map_view"/>
	</changeSet>
	
	<changeSet author="liquibase-docs" id="dropView-conceptRefTermMap">
	    <preConditions onFail="MARK_RAN"><viewExists viewName="concept_reference_term_map_view"/></preConditions>	
	    <dropView viewName="concept_reference_term_map_view"/>
	</changeSet>
	
	<changeSet author="liquibase-docs" id="createView-conceptRefTermMap">
    	<createView
            viewName="concept_reference_term_map_view">SELECT 
				 1 AS concept_id,
				 1 AS concept_map_type_name,
				 1 AS code,
				 1 AS concept_reference_term_name,
				 1 AS concept_reference_source_name
		</createView>
	</changeSet>
	
	
	<changeSet author="liquibase-docs" id="dropTable-conceptView">
	    <preConditions onFail="MARK_RAN"><tableExists tableName="concept_view"/></preConditions>
	    <dropTable cascadeConstraints="true"
	            tableName="concept_view"/>
	</changeSet>
	
	<changeSet author="liquibase-docs" id="dropView-conceptView">
	    <preConditions onFail="MARK_RAN"><viewExists viewName="concept_view"/></preConditions>
	    <dropView viewName="concept_view"/>
	</changeSet>
	
	<changeSet author="liquibase-docs" id="createView-conceptView">
    	<createView
            viewName="concept_view">SELECT 
			 1 AS concept_id,
			 1 AS concept_full_name,
			 1 AS concept_short_name,
			 1 AS concept_class_name,
			 1 AS concept_datatype_name,
			 1 AS retired,
			 1 AS description,
			 1 AS date_created
		</createView>
	</changeSet>
		
	
	<changeSet author="liquibase-docs" id="dropView-diagnosisConceptViewTemp">
	    <preConditions onFail="MARK_RAN"><viewExists viewName="diagnosis_concept_view"/></preConditions>
	    <dropView viewName="diagnosis_concept_view"/>
	</changeSet>
	
	<changeSet author="liquibase-docs" id="createView-diagnosisConceptViewFinal">
    	<createView
            viewName="diagnosis_concept_view">
            select `concept_view`.`concept_id` AS `concept_id`,`concept_view`.`concept_full_name` AS `concept_full_name`,`concept_view`.`concept_short_name` AS `concept_short_name`,`concept_view`.`concept_class_name` AS `concept_class_name`,`concept_view`.`concept_datatype_name` AS `concept_datatype_name`,`concept_view`.`retired` AS `retired`,`concept_view`.`description` AS `description`,`concept_view`.`date_created` AS `date_created`,`concept_reference_term_map_view`.`code` AS `icd10_code` from (`concept_view` left join `concept_reference_term_map_view` on(((`concept_reference_term_map_view`.`concept_id` = `concept_view`.`concept_id`) and (`concept_reference_term_map_view`.`concept_reference_source_name` = 'ICD-10-WHO') and (`concept_reference_term_map_view`.`concept_map_type_name` = 'SAME-AS')))) where (`concept_view`.`concept_class_name` = 'Diagnosis');
		</createView>
	</changeSet>
	
	
	<changeSet author="liquibase-docs" id="dropView-conceptRefTermMapTemp" runOnChange="true">
	    <preConditions onFail="MARK_RAN"><viewExists viewName="concept_reference_term_map_view"/></preConditions>
	    <dropView viewName="concept_reference_term_map_view"/>
	</changeSet>
	
	<changeSet author="liquibase-docs" id="createView-conceptRefTermMapFinal">
    	<createView
            viewName="concept_reference_term_map_view">
            select `concept_reference_map`.`concept_id` AS `concept_id`,`concept_map_type`.`name` AS `concept_map_type_name`,`concept_reference_term`.`code` AS `code`,`concept_reference_term`.`name` AS `concept_reference_term_name`,`concept_reference_source`.`name` AS `concept_reference_source_name` from (((`concept_reference_term` join `concept_reference_map` on((`concept_reference_map`.`concept_reference_term_id` = `concept_reference_term`.`concept_reference_term_id`))) join `concept_map_type` on((`concept_reference_map`.`concept_map_type_id` = `concept_map_type`.`concept_map_type_id`))) join `concept_reference_source` on((`concept_reference_source`.`concept_source_id` = `concept_reference_term`.`concept_source_id`)));
		</createView>
	</changeSet>
	
	
	<changeSet author="liquibase-docs" id="dropView-conceptViewTemp">
	    <preConditions onFail="MARK_RAN"><viewExists viewName="concept_view"/></preConditions>
	    <dropView viewName="concept_view"/>
	</changeSet>
	
	<changeSet author="liquibase-docs" id="createView-conceptViewFinal">
    	<createView
            viewName="concept_view">
            select `concept`.`concept_id` AS `concept_id`,`concept_full_name`.`name` AS `concept_full_name`,`concept_short_name`.`name` AS `concept_short_name`,`concept_class`.`name` AS `concept_class_name`,`concept_datatype`.`name` AS `concept_datatype_name`,`concept`.`retired` AS `retired`,`concept_description`.`description` AS `description`,`concept`.`date_created` AS `date_created` from (((((`concept` left join `concept_name` `concept_full_name` on(((`concept_full_name`.`concept_id` = `concept`.`concept_id`) and (`concept_full_name`.`concept_name_type` = 'FULLY_SPECIFIED') and (`concept_full_name`.`locale` = 'en') and (`concept_full_name`.`voided` = 0)))) left join `concept_name` `concept_short_name` on(((`concept_short_name`.`concept_id` = `concept`.`concept_id`) and (`concept_short_name`.`concept_name_type` = 'SHORT') and (`concept_short_name`.`locale` = 'en') and (`concept_short_name`.`voided` = 0)))) left join `concept_class` on((`concept_class`.`concept_class_id` = `concept`.`class_id`))) left join `concept_datatype` on((`concept_datatype`.`concept_datatype_id` = `concept`.`datatype_id`))) left join `concept_description` on((`concept_description`.`concept_id` = `concept`.`concept_id`)));
		</createView>
	</changeSet>	
		
	
	<!-- <changeSet author="bahmni-scheduling" id="insert-globalProperty-dc(fup)">
		<preConditions onFail="MARK_RAN">
		    <sqlCheck expectedResult="0">
		        select count(*) from global_property where property = 'Doctor Consultation (FUP)';
		    </sqlCheck>
		</preConditions>
		<insert tableName="global_property">
	        <column name="property" value="Doctor Consultation (FUP)"/>
	        <column name="property_value" value="ڈاکٹر  کے ساتھ فالو اپ مشاورت"/>
	        <column name="description" valueNumeric="null"/>
            <column name="uuid" valueNumeric="uuid()"/>
            <column name="datatype" valueNumeric="null"/>
            <column name="datatype_config" valueNumeric="null"/>
	        <column name="preferred_handler" valueNumeric="null"/>	
            <column name="handler_config" valueNumeric="null"/>
            <column name="date_changed" valueNumeric="null"/>
        	<column name="changed_by" valueNumeric="null"/>
	    </insert>
	</changeSet>
 -->
	
</databaseChangeLog>